webflow/__init__.py
webflow/config.py
webflow/entity.py
webflow/utils.py
webflow/cms/__init__.py
webflow/cms/collection.py
webflow/cms/item.py
webflow/cms/site.py
fast_webflow-0.5.1.dist-info/LICENSE
fast_webflow-0.5.1.dist-info/METADATA
fast_webflow-0.5.1.dist-info/WHEEL
fast_webflow-0.5.1.dist-info/top_level.txt
fast_webflow-0.5.1.dist-info/RECORD
