Metadata-Version: 2.1
Name: fast-webflow
Version: 0.5.1
Summary: A client library to communicate with the WebFlow API
Home-page: https://github.com/tcilloni/fast-webflow
Author: Thomas Cilloni
Author-email: tcilloni@outlook.com
Project-URL: Bug Tracker, https://github.com/tcilloni/fast-webflow/issues
Classifier: Programming Language :: Python :: 3
Classifier: License :: OSI Approved :: MIT License
Classifier: Operating System :: OS Independent
Requires-Python: >=3.8
License-File: LICENSE
